xpropcache/__init__.py
xpropcache-0.3.0.dist-info/LICENSE
xpropcache-0.3.0.dist-info/METADATA
xpropcache-0.3.0.dist-info/WHEEL
xpropcache-0.3.0.dist-info/top_level.txt
xpropcache-0.3.0.dist-info/RECORD
