Metadata-Version: 2.2
Name: xpropcache
Version: 0.3.0
Summary: Lightweight utilities for cached properties with selective reset and pickle-safe classes.
Author-email: "Adrian F. Hoefflin" <srccircumflex@outlook.com>
License: MIT License
Project-URL: Homepage, https://github.com/srccircumflex/xpropcache
Keywords: cached_property,pickle,property cache
Classifier: Topic :: Utilities
Classifier: Topic :: Software Development
Classifier: Topic :: Software Development :: Build Tools
Classifier: Programming Language :: Python
License-File: LICENSE
